proteoformquant/__init__.py
proteoformquant/_version.py
proteoformquant/archive_methods.py
proteoformquant/proteoformquant.py
proteoformquant/proteoformquant_report.py
proteoformquant/proteoformquant_report_2.py
proteoformquant/proteoformquant_report_3.py
proteoformquant/Classes/__init__.py
proteoformquant/Classes/elution_profile.py
proteoformquant/Classes/msrun.py
proteoformquant/Classes/proteoform.py
proteoformquant/Classes/psm.py
proteoformquant/Classes/spectrum.py
proteoformquant/Utils/__init__.py
proteoformquant/Utils/constant.py
proteoformquant/Utils/exception.py
proteoformquant/Utils/input.py
proteoformquant/Utils/misc.py
proteoformquant/Utils/parameters_default.py
proteoformquant-1.17.dist-info/METADATA
proteoformquant-1.17.dist-info/WHEEL
proteoformquant-1.17.dist-info/entry_points.txt
proteoformquant-1.17.dist-info/top_level.txt
proteoformquant-1.17.dist-info/RECORD
