Metadata-Version: 2.1
Name: proteoformquant
Version: 1.17
Summary: A python command line tool for the quantification of peptidoform/proteoforms
Home-page: 
Author: Arthur Grimaud
Author-email: arthur582@hotmail.fr
Classifier: Programming Language :: Python :: 3.8
Requires-Dist: alive-progress
Requires-Dist: dash (==2.6.2)
Requires-Dist: dash-bootstrap-components (==1.0.2)
Requires-Dist: dash-daq (==0.5.0)
Requires-Dist: fnnls (==1.0.0)
Requires-Dist: jsonc-parser (==1.1.5)
Requires-Dist: kneed (==0.7.0)
Requires-Dist: matplotlib (==3.5.1)
Requires-Dist: mpmath (==1.2.1)
Requires-Dist: networkx
Requires-Dist: numpy
Requires-Dist: pandas
Requires-Dist: plotly (==5.5.0)
Requires-Dist: progress (==1.6)
Requires-Dist: pymoo (==0.5.0)
Requires-Dist: pyteomics
Requires-Dist: PyYAML (==6.0)
Requires-Dist: scikit-learn
Requires-Dist: scipy
Requires-Dist: spectrum-utils (==0.3.5)
Requires-Dist: SQLAlchemy (==1.3.12)
Requires-Dist: sympy (==1.9)
Requires-Dist: unimod-mapper (==0.6.4)
Requires-Dist: lxml
Requires-Dist: ms-deisotope
